.pre-commit-config.yaml
AUTHORS.md
CHANGES.md
CONTRIBUTING.rst
LICENSE.md
MANIFEST.in
README.md
noxfile.py
pyproject.toml
requirements-testing.txt
setup.cfg
setup.py
cascade/__init__.py
cascade/_version.py
cascade/beach_dune_manager.py
cascade/brie_coupler.py
cascade/cascade.py
cascade/chom_coupler.py
cascade/roadway_manager.py
cascade/tools/__init__.py
cascade/tools/plotters.py
coastal_cascade.egg-info/PKG-INFO
coastal_cascade.egg-info/SOURCES.txt
coastal_cascade.egg-info/dependency_links.txt
coastal_cascade.egg-info/requires.txt
coastal_cascade.egg-info/top_level.txt
tests/test_coupling.py
tests/test_human_dynamics.py
tests/test_coupling/StormSeries_1kyrs_VCR_Berm1pt9m_Slope0pt04_01.npy
tests/test_coupling/ast-barrier3d-parameters.yaml
tests/test_coupling/b3d_pt75_3284yrs_low-elevations.csv
tests/test_coupling/barrier3d-default-parameters.yaml
tests/test_coupling/growthparam_1000dam.npy
tests/test_coupling/pathways-dunes.npy
tests/test_human_dynamics/StormSeries_1kyrs_VCR_Berm1pt9m_Slope0pt04_01.npy
tests/test_human_dynamics/b3d_pt45_8750yrs_low-elevations.csv
tests/test_human_dynamics/b3d_pt75_3284yrs_low-elevations.csv
tests/test_human_dynamics/growthparam_1000dam.npy
tests/test_human_dynamics/nourishment-parameters.yaml
tests/test_human_dynamics/pathways-dunes.npy
tests/test_human_dynamics/roadway-parameters.yaml