Metadata-Version: 2.1
Name: coastal-cascade
Version: 0.1.1
Summary: The CoAStal Community-lAnDscape Evolution (CASCADE) model
Author: Katherine Anarde
Author-email: kanarde@ncsu.edu
Maintainer: Katherine Anarde
Maintainer-email: kanarde@ncsu.edu
License: # The MIT License (MIT)
Project-URL: homepage, https://github.com/UNC-CECL/cascade
Project-URL: documentation, https://github.com/UNC-CECL/cascade
Project-URL: repository, https://github.com/UNC-CECL/cascade
Project-URL: changelog, https://raw.githubusercontent.com/UNC-CECL/cascade/master/CHANGES.rst
Keywords: barrier islands,coastal management,economics,overwash,sea level rise
Classifier: Development Status :: 4 - Beta
Classifier: Intended Audience :: Science/Research
Classifier: License :: OSI Approved :: MIT License
Classifier: Operating System :: OS Independent
Classifier: Programming Language :: Python :: 3
Classifier: Programming Language :: Python :: 3.8
Classifier: Programming Language :: Python :: 3.9
Classifier: Programming Language :: Python :: 3.10
Classifier: Programming Language :: Python :: 3.11
Classifier: Programming Language :: Python :: 3 :: Only
Classifier: Topic :: Scientific/Engineering :: Physics
Requires-Python: >=3.8
Provides-Extra: dev
License-File: LICENSE.md
License-File: AUTHORS.md
